[
{"reporting_country":"Colombia","region":"Americas","subregion":"SouthAmerica","partner_country":{"country_name":"Albania","region":"Europe","subregion":"SouthernEurope","year":2010,"month":3,"net_weight":310,"usd_value":7390}}
{"reporting_country":"Colombia","region":"Americas","subregion":"SouthAmerica","partner_country":{"country_name":"Algeria","region":"Africa","subregion":"NorthernAfrica","year":2010,"month":2,"net_weight":9,"usd_value":7393}}
{"reporting_country":"Colombia","region":"Americas","subregion":"SouthAmerica","partner_country":{"country_name":"Algeria","region":"Africa","subregion":"NorthernAfrica","year":2010,"month":3,"net_weight":3,"usd_value":3364}}
{"reporting_country":"Colombia","region":"Americas","subregion":"SouthAmerica","partner_country":{"country_name":"Antigua and Barbuda","region":"Americas","subregion":"Caribbean","year":2010,"month":1,"net_weight":122844,"usd_value":110260}}
{"reporting_country":"Colombia","region":"Americas","subregion":"SouthAmerica","partner_country":{"country_name":"Antigua and Barbuda","region":"Americas","subregion":"Caribbean","year":2010,"month":2,"net_weight":14176,"usd_value":43689}}
{"reporting_country":"Colombia","region":"Americas","subregion":"SouthAmerica","partner_country":{"country_name":"Antigua and Barbuda","region":"Americas","subregion":"Caribbean","year":2010,"month":3,"net_weight":18383,"usd_value":66752}}
{"reporting_country":"Colombia","region":"Americas","subregion":"SouthAmerica","partner_country":{"country_name":"Argentina","region":"Americas","subregion":"SouthAmerica","year":2010,"month":1,"net_weight":2742582,"usd_value":7139359}}
{"reporting_country":"Colombia","region":"Americas","subregion":"SouthAmerica","partner_country":{"country_name":"Argentina","region":"Americas","subregion":"SouthAmerica","year":2010,"month":2,"net_weight":1908487,"usd_value":4910265}}
{"reporting_country":"Colombia","region":"Americas","subregion":"SouthAmerica","partner_country":{"country_name":"Argentina","region":"Americas","subregion":"SouthAmerica","year":2010,"month":3,"net_weight":4303396,"usd_value":7791657}}
{"reporting_country":"Colombia","region":"Americas","subregion":"SouthAmerica","partner_country":{"country_name":"Armenia","region":"Asia","subregion":"WesternAsia","year":2010,"month":3,"net_weight":13926,"usd_value":118129}}
{"reporting_country":"Colombia","region":"Americas","subregion":"SouthAmerica","partner_country":{"country_name":"Aruba","region":"Americas","subregion":"Caribbean","year":2010,"month":1,"net_weight":614889,"usd_value":874745}}
{"reporting_country":"Colombia","region":"Americas","subregion":"SouthAmerica","partner_country":{"country_name":"Aruba","region":"Americas","subregion":"Caribbean","year":2010,"month":2,"net_weight":2017780,"usd_value":1058136}}
{"reporting_country":"Colombia","region":"Americas","subregion":"SouthAmerica","partner_country":{"country_name":"Aruba","region":"Americas","subregion":"Caribbean","year":2010,"month":3,"net_weight":7400524,"usd_value":5737823}}
{"reporting_country":"Colombia","region":"Americas","subregion":"SouthAmerica","partner_country":{"country_name":"Australia","region":"Oceania","subregion":"AustraliaandNewZealand","year":2010,"month":1,"net_weight":479996,"usd_value":1657190}}
{"reporting_country":"Colombia","region":"Americas","subregion":"SouthAmerica","partner_country":{"country_name":"Australia","region":"Oceania","subregion":"AustraliaandNewZealand","year":2010,"month":2,"net_weight":591442,"usd_value":1438155}}
{"reporting_country":"Colombia","region":"Americas","subregion":"SouthAmerica","partner_country":{"country_name":"Australia","region":"Oceania","subregion":"AustraliaandNewZealand","year":2010,"month":3,"net_weight":753109,"usd_value":2124214}}
{"reporting_country":"Colombia","region":"Americas","subregion":"SouthAmerica","partner_country":{"country_name":"Austria","region":"Europe","subregion":"WesternEurope","year":2010,"month":1,"net_weight":2116,"usd_value":32092}}
{"reporting_country":"Colombia","region":"Americas","subregion":"SouthAmerica","partner_country":{"country_name":"Austria","region":"Europe","subregion":"WesternEurope","year":2010,"month":2,"net_weight":43460,"usd_value":188182}}
{"reporting_country":"Colombia","region":"Americas","subregion":"SouthAmerica","partner_country":{"country_name":"Austria","region":"Europe","subregion":"WesternEurope","year":2010,"month":3,"net_weight":17693,"usd_value":114814}}
{"reporting_country":"Colombia","region":"Americas","subregion":"SouthAmerica","partner_country":{"country_name":"Azerbaijan","region":"Asia","subregion":"WesternAsia","year":2010,"month":1,"net_weight":306,"usd_value":1405}}
{"reporting_country":"Colombia","region":"Americas","subregion":"SouthAmerica","partner_country":{"country_name":"Azerbaijan","region":"Asia","subregion":"WesternAsia","year":2010,"month":2,"net_weight":932,"usd_value":4838}}
{"reporting_country":"Colombia","region":"Americas","subregion":"SouthAmerica","partner_country":{"country_name":"Azerbaijan","region":"Asia","subregion":"WesternAsia","year":2010,"month":3,"net_weight":5193,"usd_value":121381}}
{"reporting_country":"Colombia","region":"Americas","subregion":"SouthAmerica","partner_country":{"country_name":"Bahrain","region":"Asia","subregion":"WesternAsia","year":2010,"month":1,"net_weight":54337,"usd_value":227186}}
{"reporting_country":"Colombia","region":"Americas","subregion":"SouthAmerica","partner_country":{"country_name":"Bahrain","region":"Asia","subregion":"WesternAsia","year":2010,"month":2,"net_weight":26294,"usd_value":78469}}
{"reporting_country":"Colombia","region":"Americas","subregion":"SouthAmerica","partner_country":{"country_name":"Bahrain","region":"Asia","subregion":"WesternAsia","year":2010,"month":3,"net_weight":74254,"usd_value":508785}}
{"reporting_country":"Colombia","region":"Americas","subregion":"SouthAmerica","partner_country":{"country_name":"Barbados","region":"Americas","subregion":"Caribbean","year":2010,"month":1,"net_weight":264437,"usd_value":270000}}
{"reporting_country":"Colombia","region":"Americas","subregion":"SouthAmerica","partner_country":{"country_name":"Barbados","region":"Americas","subregion":"Caribbean","year":2010,"month":2,"net_weight":288985,"usd_value":380579}}
{"reporting_country":"Colombia","region":"Americas","subregion":"SouthAmerica","partner_country":{"country_name":"Barbados","region":"Americas","subregion":"Caribbean","year":2010,"month":3,"net_weight":687955,"usd_value":600965}}
{"reporting_country":"Colombia","region":"Americas","subregion":"SouthAmerica","partner_country":{"country_name":"Belarus","region":"Europe","subregion":"EasternEurope","year":2010,"month":1,"net_weight":667,"usd_value":5564}}
{"reporting_country":"Colombia","region":"Americas","subregion":"SouthAmerica","partner_country":{"country_name":"Belarus","region":"Europe","subregion":"EasternEurope","year":2010,"month":2,"net_weight":2089,"usd_value":19218}}
{"reporting_country":"Colombia","region":"Americas","subregion":"SouthAmerica","partner_country":{"country_name":"Belarus","region":"Europe","subregion":"EasternEurope","year":2010,"month":3,"net_weight":8085,"usd_value":51600}}
{"reporting_country":"Colombia","region":"Americas","subregion":"SouthAmerica","partner_country":{"country_name":"Belgium","region":"Europe","subregion":"WesternEurope","year":2010,"month":1,"net_weight":40897709,"usd_value":31066167}}
{"reporting_country":"Colombia","region":"Americas","subregion":"SouthAmerica","partner_country":{"country_name":"Belgium","region":"Europe","subregion":"WesternEurope","year":2010,"month":2,"net_weight":119635648,"usd_value":33764324}}
{"reporting_country":"Colombia","region":"Americas","subregion":"SouthAmerica","partner_country":{"country_name":"Belgium","region":"Europe","subregion":"WesternEurope","year":2010,"month":3,"net_weight":88462403,"usd_value":43140563}}
{"reporting_country":"Colombia","region":"Americas","subregion":"SouthAmerica","partner_country":{"country_name":"Bolivia (Plurinational State of)","region":"Americas","subregion":"SouthAmerica","year":2010,"month":1,"net_weight":3593549,"usd_value":8147516}}
{"reporting_country":"Colombia","region":"Americas","subregion":"SouthAmerica","partner_country":{"country_name":"Bolivia (Plurinational State of)","region":"Americas","subregion":"SouthAmerica","year":2010,"month":2,"net_weight":4808880,"usd_value":7867835}}
{"reporting_country":"Colombia","region":"Americas","subregion":"SouthAmerica","partner_country":{"country_name":"Bolivia (Plurinational State of)","region":"Americas","subregion":"SouthAmerica","year":2010,"month":3,"net_weight":3550753,"usd_value":6156278}}
{"reporting_country":"Colombia","region":"Americas","subregion":"SouthAmerica","partner_country":{"country_name":"Brazil","region":"Americas","subregion":"SouthAmerica","year":2010,"month":1,"net_weight":153627141,"usd_value":53922741}}
{"reporting_country":"Colombia","region":"Americas","subregion":"SouthAmerica","partner_country":{"country_name":"Brazil","region":"Americas","subregion":"SouthAmerica","year":2010,"month":2,"net_weight":113168875,"usd_value":53196925}}
{"reporting_country":"Colombia","region":"Americas","subregion":"SouthAmerica","partner_country":{"country_name":"Brazil","region":"Americas","subregion":"SouthAmerica","year":2010,"month":3,"net_weight":256878547,"usd_value":78139456}}
{"reporting_country":"Colombia","region":"Americas","subregion":"SouthAmerica","partner_country":{"country_name":"Brunei Darussalam","region":"Asia","subregion":"South-EasternAsia","year":2010,"month":1,"net_weight":10558,"usd_value":20150}}
{"reporting_country":"Colombia","region":"Americas","subregion":"SouthAmerica","partner_country":{"country_name":"Brunei Darussalam","region":"Asia","subregion":"South-EasternAsia","year":2010,"month":2,"net_weight":5030,"usd_value":12908}}
{"reporting_country":"Colombia","region":"Americas","subregion":"SouthAmerica","partner_country":{"country_name":"Bulgaria","region":"Europe","subregion":"EasternEurope","year":2010,"month":1,"net_weight":4446,"usd_value":35150}}
{"reporting_country":"Colombia","region":"Americas","subregion":"SouthAmerica","partner_country":{"country_name":"Bulgaria","region":"Europe","subregion":"EasternEurope","year":2010,"month":2,"net_weight":1964,"usd_value":9790}}
{"reporting_country":"Colombia","region":"Americas","subregion":"SouthAmerica","partner_country":{"country_name":"Bulgaria","region":"Europe","subregion":"EasternEurope","year":2010,"month":3,"net_weight":18204,"usd_value":21271}}
{"reporting_country":"Colombia","region":"Americas","subregion":"SouthAmerica","partner_country":{"country_name":"Burundi","region":"Africa","subregion":"EasternAfrica","year":2010,"month":1,"net_weight":232,"usd_value":5150}}
{"reporting_country":"Colombia","region":"Americas","subregion":"SouthAmerica","partner_country":{"country_name":"Burundi","region":"Africa","subregion":"EasternAfrica","year":2010,"month":3,"net_weight":2620,"usd_value":54540}}
{"reporting_country":"Colombia","region":"Americas","subregion":"SouthAmerica","partner_country":{"country_name":"Cameroon","region":"Africa","subregion":"MiddleAfrica","year":2010,"month":1,"net_weight":39313,"usd_value":112331}}
{"reporting_country":"Colombia","region":"Americas","subregion":"SouthAmerica","partner_country":{"country_name":"Cameroon","region":"Africa","subregion":"MiddleAfrica","year":2010,"month":2,"net_weight":81669,"usd_value":178008}}
{"reporting_country":"Colombia","region":"Americas","subregion":"SouthAmerica","partner_country":{"country_name":"Cameroon","region":"Africa","subregion":"MiddleAfrica","year":2010,"month":3,"net_weight":57614,"usd_value":185748}}
{"reporting_country":"Colombia","region":"Americas","subregion":"SouthAmerica","partner_country":{"country_name":"Canada","region":"Americas","subregion":"NorthernAmerica","year":2010,"month":1,"net_weight":128000365,"usd_value":26198261}}
{"reporting_country":"Colombia","region":"Americas","subregion":"SouthAmerica","partner_country":{"country_name":"Canada","region":"Americas","subregion":"NorthernAmerica","year":2010,"month":2,"net_weight":109339385,"usd_value":33282844}}
{"reporting_country":"Colombia","region":"Americas","subregion":"SouthAmerica","partner_country":{"country_name":"Canada","region":"Americas","subregion":"NorthernAmerica","year":2010,"month":3,"net_weight":121181012,"usd_value":39752199}}
{"reporting_country":"Colombia","region":"Americas","subregion":"SouthAmerica","partner_country":{"country_name":"Chile","region":"Americas","subregion":"SouthAmerica","year":2010,"month":1,"net_weight":515612940,"usd_value":64846318}}
{"reporting_country":"Colombia","region":"Americas","subregion":"SouthAmerica","partner_country":{"country_name":"Chile","region":"Americas","subregion":"SouthAmerica","year":2010,"month":2,"net_weight":300684538,"usd_value":65547764}}
{"reporting_country":"Colombia","region":"Americas","subregion":"SouthAmerica","partner_country":{"country_name":"Chile","region":"Americas","subregion":"SouthAmerica","year":2010,"month":3,"net_weight":379781938,"usd_value":58982465}}
{"reporting_country":"Colombia","region":"Americas","subregion":"SouthAmerica","partner_country":{"country_name":"China","region":"Asia","subregion":"EasternAsia","year":2010,"month":1,"net_weight":287521857,"usd_value":175474808}}
{"reporting_country":"Colombia","region":"Americas","subregion":"SouthAmerica","partner_country":{"country_name":"China","region":"Asia","subregion":"EasternAsia","year":2010,"month":2,"net_weight":808855658,"usd_value":221367772}}
{"reporting_country":"Colombia","region":"Americas","subregion":"SouthAmerica","partner_country":{"country_name":"China","region":"Asia","subregion":"EasternAsia","year":2010,"month":3,"net_weight":665580838,"usd_value":233017510}}
{"reporting_country":"Colombia","region":"Americas","subregion":"SouthAmerica","partner_country":{"country_name":"China, Hong Kong SAR","region":"Asia","subregion":"EasternAsia","year":2010,"month":1,"net_weight":1292322,"usd_value":5324996}}
{"reporting_country":"Colombia","region":"Americas","subregion":"SouthAmerica","partner_country":{"country_name":"China, Hong Kong SAR","region":"Asia","subregion":"EasternAsia","year":2010,"month":2,"net_weight":854294,"usd_value":3009293}}
{"reporting_country":"Colombia","region":"Americas","subregion":"SouthAmerica","partner_country":{"country_name":"China, Hong Kong SAR","region":"Asia","subregion":"EasternAsia","year":2010,"month":3,"net_weight":650238,"usd_value":4485931}}
{"reporting_country":"Colombia","region":"Americas","subregion":"SouthAmerica","partner_country":{"country_name":"Croatia","region":"Europe","subregion":"SouthernEurope","year":2010,"month":1,"net_weight":4963,"usd_value":58726}}
{"reporting_country":"Colombia","region":"Americas","subregion":"SouthAmerica","partner_country":{"country_name":"Croatia","region":"Europe","subregion":"SouthernEurope","year":2010,"month":2,"net_weight":7228,"usd_value":50096}}
{"reporting_country":"Colombia","region":"Americas","subregion":"SouthAmerica","partner_country":{"country_name":"Croatia","region":"Europe","subregion":"SouthernEurope","year":2010,"month":3,"net_weight":29364,"usd_value":43024}}
{"reporting_country":"Colombia","region":"Americas","subregion":"SouthAmerica","partner_country":{"country_name":"Cyprus","region":"Asia","subregion":"WesternAsia","year":2010,"month":2,"net_weight":12160,"usd_value":48010}}
{"reporting_country":"Colombia","region":"Americas","subregion":"SouthAmerica","partner_country":{"country_name":"Cyprus","region":"Asia","subregion":"WesternAsia","year":2010,"month":3,"net_weight":265298,"usd_value":183941}}
{"reporting_country":"Colombia","region":"Americas","subregion":"SouthAmerica","partner_country":{"country_name":"Czech Rep.","region":"Europe","subregion":"EasternEurope","year":2010,"month":1,"net_weight":23250,"usd_value":91455}}
{"reporting_country":"Colombia","region":"Americas","subregion":"SouthAmerica","partner_country":{"country_name":"Czech Rep.","region":"Europe","subregion":"EasternEurope","year":2010,"month":2,"net_weight":20127,"usd_value":124709}}
{"reporting_country":"Colombia","region":"Americas","subregion":"SouthAmerica","partner_country":{"country_name":"Czech Rep.","region":"Europe","subregion":"EasternEurope","year":2010,"month":3,"net_weight":58221,"usd_value":299897}}
{"reporting_country":"Colombia","region":"Americas","subregion":"SouthAmerica","partner_country":{"country_name":"Denmark","region":"Europe","subregion":"NorthernEurope","year":2010,"month":1,"net_weight":478163698,"usd_value":33730644}}
{"reporting_country":"Colombia","region":"Americas","subregion":"SouthAmerica","partner_country":{"country_name":"Denmark","region":"Europe","subregion":"NorthernEurope","year":2010,"month":2,"net_weight":155878142,"usd_value":10968580}}
{"reporting_country":"Colombia","region":"Americas","subregion":"SouthAmerica","partner_country":{"country_name":"Denmark","region":"Europe","subregion":"NorthernEurope","year":2010,"month":3,"net_weight":214357,"usd_value":1199451}}
{"reporting_country":"Colombia","region":"Americas","subregion":"SouthAmerica","partner_country":{"country_name":"Dominica","region":"Americas","subregion":"Caribbean","year":2010,"month":1,"net_weight":28679,"usd_value":319168}}
{"reporting_country":"Colombia","region":"Americas","subregion":"SouthAmerica","partner_country":{"country_name":"Dominica","region":"Americas","subregion":"Caribbean","year":2010,"month":2,"net_weight":102168,"usd_value":147361}}
{"reporting_country":"Colombia","region":"Americas","subregion":"SouthAmerica","partner_country":{"country_name":"Dominica","region":"Americas","subregion":"Caribbean","year":2010,"month":3,"net_weight":3118,"usd_value":79688}}
{"reporting_country":"Colombia","region":"Americas","subregion":"SouthAmerica","partner_country":{"country_name":"Dominican Rep.","region":"Americas","subregion":"Caribbean","year":2010,"month":1,"net_weight":104226214,"usd_value":39868439}}
{"reporting_country":"Colombia","region":"Americas","subregion":"SouthAmerica","partner_country":{"country_name":"Dominican Rep.","region":"Americas","subregion":"Caribbean","year":2010,"month":2,"net_weight":110161359,"usd_value":60861115}}
{"reporting_country":"Colombia","region":"Americas","subregion":"SouthAmerica","partner_country":{"country_name":"Dominican Rep.","region":"Americas","subregion":"Caribbean","year":2010,"month":3,"net_weight":262187279,"usd_value":114994166}}
{"reporting_country":"Colombia","region":"Americas","subregion":"SouthAmerica","partner_country":{"country_name":"Ecuador","region":"Americas","subregion":"SouthAmerica","year":2010,"month":1,"net_weight":42126775,"usd_value":86174283}}
{"reporting_country":"Colombia","region":"Americas","subregion":"SouthAmerica","partner_country":{"country_name":"Ecuador","region":"Americas","subregion":"SouthAmerica","year":2010,"month":2,"net_weight":44202488,"usd_value":120737899}}
{"reporting_country":"Colombia","region":"Americas","subregion":"SouthAmerica","partner_country":{"country_name":"Ecuador","region":"Americas","subregion":"SouthAmerica","year":2010,"month":3,"net_weight":74987471,"usd_value":149320262}}
{"reporting_country":"Colombia","region":"Americas","subregion":"SouthAmerica","partner_country":{"country_name":"Egypt","region":"Africa","subregion":"NorthernAfrica","year":2010,"month":1,"net_weight":141315,"usd_value":316859}}
{"reporting_country":"Colombia","region":"Americas","subregion":"SouthAmerica","partner_country":{"country_name":"Egypt","region":"Africa","subregion":"NorthernAfrica","year":2010,"month":2,"net_weight":49305,"usd_value":87045}}
{"reporting_country":"Colombia","region":"Americas","subregion":"SouthAmerica","partner_country":{"country_name":"Egypt","region":"Africa","subregion":"NorthernAfrica","year":2010,"month":3,"net_weight":222553,"usd_value":378803}}
{"reporting_country":"Colombia","region":"Americas","subregion":"SouthAmerica","partner_country":{"country_name":"El Salvador","region":"Americas","subregion":"CentralAmerica","year":2010,"month":1,"net_weight":2829165,"usd_value":3898000}}
{"reporting_country":"Colombia","region":"Americas","subregion":"SouthAmerica","partner_country":{"country_name":"El Salvador","region":"Americas","subregion":"CentralAmerica","year":2010,"month":2,"net_weight":1317504,"usd_value":2579543}}
{"reporting_country":"Colombia","region":"Americas","subregion":"SouthAmerica","partner_country":{"country_name":"El Salvador","region":"Americas","subregion":"CentralAmerica","year":2010,"month":3,"net_weight":2225870,"usd_value":4258157}}
{"reporting_country":"Colombia","region":"Americas","subregion":"SouthAmerica","partner_country":{"country_name":"Estonia","region":"Europe","subregion":"NorthernEurope","year":2010,"month":1,"net_weight":21266,"usd_value":233980}}
{"reporting_country":"Colombia","region":"Americas","subregion":"SouthAmerica","partner_country":{"country_name":"Estonia","region":"Europe","subregion":"NorthernEurope","year":2010,"month":2,"net_weight":19476,"usd_value":91597}}
{"reporting_country":"Colombia","region":"Americas","subregion":"SouthAmerica","partner_country":{"country_name":"Estonia","region":"Europe","subregion":"NorthernEurope","year":2010,"month":3,"net_weight":20278,"usd_value":98370}}
{"reporting_country":"Colombia","region":"Americas","subregion":"SouthAmerica","partner_country":{"country_name":"Ethiopia","region":"Africa","subregion":"EasternAfrica","year":2010,"month":3,"net_weight":22207,"usd_value":82256}}
{"reporting_country":"Colombia","region":"Americas","subregion":"SouthAmerica","partner_country":{"country_name":"Finland","region":"Europe","subregion":"NorthernEurope","year":2010,"month":1,"net_weight":767023,"usd_value":2784143}}
{"reporting_country":"Colombia","region":"Americas","subregion":"SouthAmerica","partner_country":{"country_name":"Finland","region":"Europe","subregion":"NorthernEurope","year":2010,"month":2,"net_weight":526754,"usd_value":2498171}}
{"reporting_country":"Colombia","region":"Americas","subregion":"SouthAmerica","partner_country":{"country_name":"Finland","region":"Europe","subregion":"NorthernEurope","year":2010,"month":3,"net_weight":996261,"usd_value":4478023}}
{"reporting_country":"Colombia","region":"Americas","subregion":"SouthAmerica","partner_country":{"country_name":"France","region":"Europe","subregion":"WesternEurope","year":2010,"month":1,"net_weight":603551097,"usd_value":65561434}}
{"reporting_country":"Colombia","region":"Americas","subregion":"SouthAmerica","partner_country":{"country_name":"France","region":"Europe","subregion":"WesternEurope","year":2010,"month":2,"net_weight":248274320,"usd_value":33681203}}
{"reporting_country":"Colombia","region":"Americas","subregion":"SouthAmerica","partner_country":{"country_name":"France","region":"Europe","subregion":"WesternEurope","year":2010,"month":3,"net_weight":186859424,"usd_value":29891263}}
{"reporting_country":"Colombia","region":"Americas","subregion":"SouthAmerica","partner_country":{"country_name":"Georgia","region":"Asia","subregion":"WesternAsia","year":2010,"month":2,"net_weight":69244,"usd_value":232776}}
{"reporting_country":"Colombia","region":"Americas","subregion":"SouthAmerica","partner_country":{"country_name":"Germany","region":"Europe","subregion":"WesternEurope","year":2010,"month":1,"net_weight":17750631,"usd_value":18297302}}
{"reporting_country":"Colombia","region":"Americas","subregion":"SouthAmerica","partner_country":{"country_name":"Germany","region":"Europe","subregion":"WesternEurope","year":2010,"month":2,"net_weight":32038891,"usd_value":19500486}}
{"reporting_country":"Colombia","region":"Americas","subregion":"SouthAmerica","partner_country":{"country_name":"Germany","region":"Europe","subregion":"WesternEurope","year":2010,"month":3,"net_weight":31017850,"usd_value":23778915}}
{"reporting_country":"Colombia","region":"Americas","subregion":"SouthAmerica","partner_country":{"country_name":"Greece","region":"Europe","subregion":"SouthernEurope","year":2010,"month":1,"net_weight":171813,"usd_value":836438}}
{"reporting_country":"Colombia","region":"Americas","subregion":"SouthAmerica","partner_country":{"country_name":"Greece","region":"Europe","subregion":"SouthernEurope","year":2010,"month":2,"net_weight":270451,"usd_value":1548135}}
{"reporting_country":"Colombia","region":"Americas","subregion":"SouthAmerica","partner_country":{"country_name":"Greece","region":"Europe","subregion":"SouthernEurope","year":2010,"month":3,"net_weight":331774,"usd_value":1493065}}
{"reporting_country":"Colombia","region":"Americas","subregion":"SouthAmerica","partner_country":{"country_name":"Guatemala","region":"Americas","subregion":"CentralAmerica","year":2010,"month":1,"net_weight":52089189,"usd_value":13239944}}
{"reporting_country":"Colombia","region":"Americas","subregion":"SouthAmerica","partner_country":{"country_name":"Guatemala","region":"Americas","subregion":"CentralAmerica","year":2010,"month":2,"net_weight":53703221,"usd_value":15557160}}
{"reporting_country":"Colombia","region":"Americas","subregion":"SouthAmerica","partner_country":{"country_name":"Guatemala","region":"Americas","subregion":"CentralAmerica","year":2010,"month":3,"net_weight":56095070,"usd_value":18441203}}
{"reporting_country":"Colombia","region":"Americas","subregion":"SouthAmerica","partner_country":{"country_name":"Hungary","region":"Europe","subregion":"EasternEurope","year":2010,"month":1,"net_weight":46916,"usd_value":179498}}
{"reporting_country":"Colombia","region":"Americas","subregion":"SouthAmerica","partner_country":{"country_name":"Hungary","region":"Europe","subregion":"EasternEurope","year":2010,"month":2,"net_weight":30305,"usd_value":116226}}
{"reporting_country":"Colombia","region":"Americas","subregion":"SouthAmerica","partner_country":{"country_name":"Hungary","region":"Europe","subregion":"EasternEurope","year":2010,"month":3,"net_weight":22966,"usd_value":145294}}
{"reporting_country":"Colombia","region":"Americas","subregion":"SouthAmerica","partner_country":{"country_name":"Iceland","region":"Europe","subregion":"NorthernEurope","year":2010,"month":2,"net_weight":19199,"usd_value":88673}}
{"reporting_country":"Colombia","region":"Americas","subregion":"SouthAmerica","partner_country":{"country_name":"India","region":"Asia","subregion":"SouthernAsia","year":2010,"month":1,"net_weight":33543134,"usd_value":8202273}}
{"reporting_country":"Colombia","region":"Americas","subregion":"SouthAmerica","partner_country":{"country_name":"India","region":"Asia","subregion":"SouthernAsia","year":2010,"month":2,"net_weight":209678360,"usd_value":85399371}}
{"reporting_country":"Colombia","region":"Americas","subregion":"SouthAmerica","partner_country":{"country_name":"India","region":"Asia","subregion":"SouthernAsia","year":2010,"month":3,"net_weight":23445469,"usd_value":8488811}}
{"reporting_country":"Colombia","region":"Americas","subregion":"SouthAmerica","partner_country":{"country_name":"Indonesia","region":"Asia","subregion":"South-EasternAsia","year":2010,"month":1,"net_weight":3325576,"usd_value":5269972}}
{"reporting_country":"Colombia","region":"Americas","subregion":"SouthAmerica","partner_country":{"country_name":"Indonesia","region":"Asia","subregion":"South-EasternAsia","year":2010,"month":2,"net_weight":1134220,"usd_value":1536681}}
{"reporting_country":"Colombia","region":"Americas","subregion":"SouthAmerica","partner_country":{"country_name":"Indonesia","region":"Asia","subregion":"South-EasternAsia","year":2010,"month":3,"net_weight":2288704,"usd_value":3075645}}
{"reporting_country":"Colombia","region":"Americas","subregion":"SouthAmerica","partner_country":{"country_name":"Ireland","region":"Europe","subregion":"NorthernEurope","year":2010,"month":1,"net_weight":163114017,"usd_value":8883199}}
{"reporting_country":"Colombia","region":"Americas","subregion":"SouthAmerica","partner_country":{"country_name":"Ireland","region":"Europe","subregion":"NorthernEurope","year":2010,"month":2,"net_weight":21760,"usd_value":85109}}
{"reporting_country":"Colombia","region":"Americas","subregion":"SouthAmerica","partner_country":{"country_name":"Israel","region":"Asia","subregion":"WesternAsia","year":2010,"month":1,"net_weight":349205194,"usd_value":26107421}}
{"reporting_country":"Colombia","region":"Americas","subregion":"SouthAmerica","partner_country":{"country_name":"Israel","region":"Asia","subregion":"WesternAsia","year":2010,"month":2,"net_weight":174298600,"usd_value":13313818}}
{"reporting_country":"Colombia","region":"Americas","subregion":"SouthAmerica","partner_country":{"country_name":"Israel","region":"Asia","subregion":"WesternAsia","year":2010,"month":3,"net_weight":185589190,"usd_value":17144418}}
{"reporting_country":"Colombia","region":"Americas","subregion":"SouthAmerica","partner_country":{"country_name":"Italy","region":"Europe","subregion":"SouthernEurope","year":2010,"month":1,"net_weight":252978283,"usd_value":52243686}}
{"reporting_country":"Colombia","region":"Americas","subregion":"SouthAmerica","partner_country":{"country_name":"Italy","region":"Europe","subregion":"SouthernEurope","year":2010,"month":2,"net_weight":171249845,"usd_value":44223312}}
{"reporting_country":"Colombia","region":"Americas","subregion":"SouthAmerica","partner_country":{"country_name":"Italy","region":"Europe","subregion":"SouthernEurope","year":2010,"month":3,"net_weight":16374447,"usd_value":18165607}}
{"reporting_country":"Colombia","region":"Americas","subregion":"SouthAmerica","partner_country":{"country_name":"Japan","region":"Asia","subregion":"EasternAsia","year":2010,"month":1,"net_weight":7911088,"usd_value":32105829}}
{"reporting_country":"Colombia","region":"Americas","subregion":"SouthAmerica","partner_country":{"country_name":"Japan","region":"Asia","subregion":"EasternAsia","year":2010,"month":2,"net_weight":6972038,"usd_value":30844311}}
{"reporting_country":"Colombia","region":"Americas","subregion":"SouthAmerica","partner_country":{"country_name":"Japan","region":"Asia","subregion":"EasternAsia","year":2010,"month":3,"net_weight":13179010,"usd_value":56175242}}
{"reporting_country":"Colombia","region":"Americas","subregion":"SouthAmerica","partner_country":{"country_name":"Jordan","region":"Asia","subregion":"WesternAsia","year":2010,"month":1,"net_weight":38749,"usd_value":174914}}
{"reporting_country":"Colombia","region":"Americas","subregion":"SouthAmerica","partner_country":{"country_name":"Jordan","region":"Asia","subregion":"WesternAsia","year":2010,"month":2,"net_weight":62935,"usd_value":261266}}
{"reporting_country":"Colombia","region":"Americas","subregion":"SouthAmerica","partner_country":{"country_name":"Jordan","region":"Asia","subregion":"WesternAsia","year":2010,"month":3,"net_weight":39171,"usd_value":205397}}
{"reporting_country":"Colombia","region":"Americas","subregion":"SouthAmerica","partner_country":{"country_name":"Kazakhstan","region":"Asia","subregion":"CentralAsia","year":2010,"month":1,"net_weight":3191,"usd_value":24599}}
{"reporting_country":"Colombia","region":"Americas","subregion":"SouthAmerica","partner_country":{"country_name":"Kazakhstan","region":"Asia","subregion":"CentralAsia","year":2010,"month":2,"net_weight":2753,"usd_value":28471}}
{"reporting_country":"Colombia","region":"Americas","subregion":"SouthAmerica","partner_country":{"country_name":"Kazakhstan","region":"Asia","subregion":"CentralAsia","year":2010,"month":3,"net_weight":961,"usd_value":33029}}
{"reporting_country":"Colombia","region":"Americas","subregion":"SouthAmerica","partner_country":{"country_name":"Kenya","region":"Africa","subregion":"EasternAfrica","year":2010,"month":1,"net_weight":2799700,"usd_value":1370376}}
{"reporting_country":"Colombia","region":"Americas","subregion":"SouthAmerica","partner_country":{"country_name":"Kenya","region":"Africa","subregion":"EasternAfrica","year":2010,"month":2,"net_weight":700004,"usd_value":376818}}
{"reporting_country":"Colombia","region":"Americas","subregion":"SouthAmerica","partner_country":{"country_name":"Kenya","region":"Africa","subregion":"EasternAfrica","year":2010,"month":3,"net_weight":1534718,"usd_value":706202}}
{"reporting_country":"Colombia","region":"Americas","subregion":"SouthAmerica","partner_country":{"country_name":"Kyrgyzstan","region":"Asia","subregion":"CentralAsia","year":2010,"month":2,"net_weight":2360,"usd_value":14214}}
{"reporting_country":"Colombia","region":"Americas","subregion":"SouthAmerica","partner_country":{"country_name":"Kyrgyzstan","region":"Asia","subregion":"CentralAsia","year":2010,"month":3,"net_weight":2393,"usd_value":17684}}
{"reporting_country":"Colombia","region":"Americas","subregion":"SouthAmerica","partner_country":{"country_name":"Latvia","region":"Europe","subregion":"NorthernEurope","year":2010,"month":2,"net_weight":35300,"usd_value":105960}}
{"reporting_country":"Colombia","region":"Americas","subregion":"SouthAmerica","partner_country":{"country_name":"Latvia","region":"Europe","subregion":"NorthernEurope","year":2010,"month":3,"net_weight":22146,"usd_value":131833}}
{"reporting_country":"Colombia","region":"Americas","subregion":"SouthAmerica","partner_country":{"country_name":"Lithuania","region":"Europe","subregion":"NorthernEurope","year":2010,"month":1,"net_weight":0,"usd_value":5000}}
{"reporting_country":"Colombia","region":"Americas","subregion":"SouthAmerica","partner_country":{"country_name":"Lithuania","region":"Europe","subregion":"NorthernEurope","year":2010,"month":2,"net_weight":2760,"usd_value":32894}}
{"reporting_country":"Colombia","region":"Americas","subregion":"SouthAmerica","partner_country":{"country_name":"Lithuania","region":"Europe","subregion":"NorthernEurope","year":2010,"month":3,"net_weight":0,"usd_value":5000}}
{"reporting_country":"Colombia","region":"Americas","subregion":"SouthAmerica","partner_country":{"country_name":"Madagascar","region":"Africa","subregion":"EasternAfrica","year":2010,"month":2,"net_weight":542,"usd_value":1727}}
{"reporting_country":"Colombia","region":"Americas","subregion":"SouthAmerica","partner_country":{"country_name":"Malaysia","region":"Asia","subregion":"South-EasternAsia","year":2010,"month":1,"net_weight":40575,"usd_value":202246}}
{"reporting_country":"Colombia","region":"Americas","subregion":"SouthAmerica","partner_country":{"country_name":"Malaysia","region":"Asia","subregion":"South-EasternAsia","year":2010,"month":2,"net_weight":32862,"usd_value":297190}}
{"reporting_country":"Colombia","region":"Americas","subregion":"SouthAmerica","partner_country":{"country_name":"Malaysia","region":"Asia","subregion":"South-EasternAsia","year":2010,"month":3,"net_weight":15623,"usd_value":140504}}
{"reporting_country":"Colombia","region":"Americas","subregion":"SouthAmerica","partner_country":{"country_name":"Malta","region":"Europe","subregion":"SouthernEurope","year":2010,"month":1,"net_weight":104,"usd_value":3486}}
{"reporting_country":"Colombia","region":"Americas","subregion":"SouthAmerica","partner_country":{"country_name":"Mexico","region":"Americas","subregion":"CentralAmerica","year":2010,"month":1,"net_weight":35031497,"usd_value":43349914}}
{"reporting_country":"Colombia","region":"Americas","subregion":"SouthAmerica","partner_country":{"country_name":"Mexico","region":"Americas","subregion":"CentralAmerica","year":2010,"month":2,"net_weight":10802781,"usd_value":33390996}}
{"reporting_country":"Colombia","region":"Americas","subregion":"SouthAmerica","partner_country":{"country_name":"Mexico","region":"Americas","subregion":"CentralAmerica","year":2010,"month":3,"net_weight":63421649,"usd_value":56702790}}
{"reporting_country":"Colombia","region":"Americas","subregion":"SouthAmerica","partner_country":{"country_name":"Morocco","region":"Africa","subregion":"NorthernAfrica","year":2010,"month":1,"net_weight":129770015,"usd_value":7689392}}
{"reporting_country":"Colombia","region":"Americas","subregion":"SouthAmerica","partner_country":{"country_name":"Morocco","region":"Africa","subregion":"NorthernAfrica","year":2010,"month":2,"net_weight":21773634,"usd_value":12303778}}
{"reporting_country":"Colombia","region":"Americas","subregion":"SouthAmerica","partner_country":{"country_name":"Morocco","region":"Africa","subregion":"NorthernAfrica","year":2010,"month":3,"net_weight":147109,"usd_value":414373}}
{"reporting_country":"Colombia","region":"Americas","subregion":"SouthAmerica","partner_country":{"country_name":"Mozambique","region":"Africa","subregion":"EasternAfrica","year":2010,"month":1,"net_weight":135662,"usd_value":240434}}
{"reporting_country":"Colombia","region":"Americas","subregion":"SouthAmerica","partner_country":{"country_name":"Mozambique","region":"Africa","subregion":"EasternAfrica","year":2010,"month":2,"net_weight":185369,"usd_value":326593}}
{"reporting_country":"Colombia","region":"Americas","subregion":"SouthAmerica","partner_country":{"country_name":"Mozambique","region":"Africa","subregion":"EasternAfrica","year":2010,"month":3,"net_weight":184514,"usd_value":332289}}
{"reporting_country":"Colombia","region":"Americas","subregion":"SouthAmerica","partner_country":{"country_name":"Netherlands","region":"Europe","subregion":"WesternEurope","year":2010,"month":1,"net_weight":1277444853,"usd_value":127224269}}
{"reporting_country":"Colombia","region":"Americas","subregion":"SouthAmerica","partner_country":{"country_name":"Netherlands","region":"Europe","subregion":"WesternEurope","year":2010,"month":2,"net_weight":1599827845,"usd_value":115819886}}
{"reporting_country":"Colombia","region":"Americas","subregion":"SouthAmerica","partner_country":{"country_name":"Netherlands","region":"Europe","subregion":"WesternEurope","year":2010,"month":3,"net_weight":1185233897,"usd_value":137596650}}
{"reporting_country":"Colombia","region":"Americas","subregion":"SouthAmerica","partner_country":{"country_name":"New Zealand","region":"Oceania","subregion":"AustraliaandNewZealand","year":2010,"month":1,"net_weight":152259,"usd_value":723366}}
{"reporting_country":"Colombia","region":"Americas","subregion":"SouthAmerica","partner_country":{"country_name":"New Zealand","region":"Oceania","subregion":"AustraliaandNewZealand","year":2010,"month":2,"net_weight":106398,"usd_value":361082}}
{"reporting_country":"Colombia","region":"Americas","subregion":"SouthAmerica","partner_country":{"country_name":"New Zealand","region":"Oceania","subregion":"AustraliaandNewZealand","year":2010,"month":3,"net_weight":144153,"usd_value":745166}}
{"reporting_country":"Colombia","region":"Americas","subregion":"SouthAmerica","partner_country":{"country_name":"Nicaragua","region":"Americas","subregion":"CentralAmerica","year":2010,"month":1,"net_weight":86077,"usd_value":538551}}
{"reporting_country":"Colombia","region":"Americas","subregion":"SouthAmerica","partner_country":{"country_name":"Nicaragua","region":"Americas","subregion":"CentralAmerica","year":2010,"month":2,"net_weight":39238,"usd_value":443212}}
{"reporting_country":"Colombia","region":"Americas","subregion":"SouthAmerica","partner_country":{"country_name":"Nicaragua","region":"Americas","subregion":"CentralAmerica","year":2010,"month":3,"net_weight":123085,"usd_value":906169}}
{"reporting_country":"Colombia","region":"Americas","subregion":"SouthAmerica","partner_country":{"country_name":"Nigeria","region":"Africa","subregion":"WesternAfrica","year":2010,"month":1,"net_weight":16034,"usd_value":44951}}
{"reporting_country":"Colombia","region":"Americas","subregion":"SouthAmerica","partner_country":{"country_name":"Nigeria","region":"Africa","subregion":"WesternAfrica","year":2010,"month":2,"net_weight":31720,"usd_value":83382}}
{"reporting_country":"Colombia","region":"Americas","subregion":"SouthAmerica","partner_country":{"country_name":"Nigeria","region":"Africa","subregion":"WesternAfrica","year":2010,"month":3,"net_weight":104862,"usd_value":274654}}
{"reporting_country":"Colombia","region":"Americas","subregion":"SouthAmerica","partner_country":{"country_name":"Norway","region":"Europe","subregion":"NorthernEurope","year":2010,"month":1,"net_weight":612739,"usd_value":2449031}}
{"reporting_country":"Colombia","region":"Americas","subregion":"SouthAmerica","partner_country":{"country_name":"Norway","region":"Europe","subregion":"NorthernEurope","year":2010,"month":2,"net_weight":351343,"usd_value":1394919}}
{"reporting_country":"Colombia","region":"Americas","subregion":"SouthAmerica","partner_country":{"country_name":"Norway","region":"Europe","subregion":"NorthernEurope","year":2010,"month":3,"net_weight":10960428,"usd_value":5891936}}
{"reporting_country":"Colombia","region":"Americas","subregion":"SouthAmerica","partner_country":{"country_name":"Pakistan","region":"Asia","subregion":"SouthernAsia","year":2010,"month":1,"net_weight":979524,"usd_value":259431}}
{"reporting_country":"Colombia","region":"Americas","subregion":"SouthAmerica","partner_country":{"country_name":"Pakistan","region":"Asia","subregion":"SouthernAsia","year":2010,"month":2,"net_weight":5446,"usd_value":51333}}
{"reporting_country":"Colombia","region":"Americas","subregion":"SouthAmerica","partner_country":{"country_name":"Pakistan","region":"Asia","subregion":"SouthernAsia","year":2010,"month":3,"net_weight":3802728,"usd_value":2038934}}
{"reporting_country":"Colombia","region":"Americas","subregion":"SouthAmerica","partner_country":{"country_name":"Panama","region":"Americas","subregion":"CentralAmerica","year":2010,"month":1,"net_weight":31629556,"usd_value":31230089}}
{"reporting_country":"Colombia","region":"Americas","subregion":"SouthAmerica","partner_country":{"country_name":"Panama","region":"Americas","subregion":"CentralAmerica","year":2010,"month":2,"net_weight":49366248,"usd_value":30670129}}
{"reporting_country":"Colombia","region":"Americas","subregion":"SouthAmerica","partner_country":{"country_name":"Panama","region":"Americas","subregion":"CentralAmerica","year":2010,"month":3,"net_weight":47730569,"usd_value":32024664}}
{"reporting_country":"Colombia","region":"Americas","subregion":"SouthAmerica","partner_country":{"country_name":"Paraguay","region":"Americas","subregion":"SouthAmerica","year":2010,"month":1,"net_weight":365053,"usd_value":1440503}}
{"reporting_country":"Colombia","region":"Americas","subregion":"SouthAmerica","partner_country":{"country_name":"Paraguay","region":"Americas","subregion":"SouthAmerica","year":2010,"month":2,"net_weight":215108,"usd_value":376383}}
{"reporting_country":"Colombia","region":"Americas","subregion":"SouthAmerica","partner_country":{"country_name":"Paraguay","region":"Americas","subregion":"SouthAmerica","year":2010,"month":3,"net_weight":134671,"usd_value":714336}}
{"reporting_country":"Colombia","region":"Americas","subregion":"SouthAmerica","partner_country":{"country_name":"Peru","region":"Americas","subregion":"SouthAmerica","year":2010,"month":1,"net_weight":95683204,"usd_value":72500426}}
{"reporting_country":"Colombia","region":"Americas","subregion":"SouthAmerica","partner_country":{"country_name":"Peru","region":"Americas","subregion":"SouthAmerica","year":2010,"month":2,"net_weight":44784805,"usd_value":68168549}}
{"reporting_country":"Colombia","region":"Americas","subregion":"SouthAmerica","partner_country":{"country_name":"Peru","region":"Americas","subregion":"SouthAmerica","year":2010,"month":3,"net_weight":149292177,"usd_value":89996386}}
{"reporting_country":"Colombia","region":"Americas","subregion":"SouthAmerica","partner_country":{"country_name":"Philippines","region":"Asia","subregion":"South-EasternAsia","year":2010,"month":1,"net_weight":332308,"usd_value":1086962}}
{"reporting_country":"Colombia","region":"Americas","subregion":"SouthAmerica","partner_country":{"country_name":"Philippines","region":"Asia","subregion":"South-EasternAsia","year":2010,"month":2,"net_weight":34928,"usd_value":145425}}
{"reporting_country":"Colombia","region":"Americas","subregion":"SouthAmerica","partner_country":{"country_name":"Philippines","region":"Asia","subregion":"South-EasternAsia","year":2010,"month":3,"net_weight":502899,"usd_value":1640742}}
{"reporting_country":"Colombia","region":"Americas","subregion":"SouthAmerica","partner_country":{"country_name":"Poland","region":"Europe","subregion":"EasternEurope","year":2010,"month":1,"net_weight":103622,"usd_value":330405}}
{"reporting_country":"Colombia","region":"Americas","subregion":"SouthAmerica","partner_country":{"country_name":"Poland","region":"Europe","subregion":"EasternEurope","year":2010,"month":2,"net_weight":192808,"usd_value":655492}}
{"reporting_country":"Colombia","region":"Americas","subregion":"SouthAmerica","partner_country":{"country_name":"Poland","region":"Europe","subregion":"EasternEurope","year":2010,"month":3,"net_weight":42793230,"usd_value":6471866}}
{"reporting_country":"Colombia","region":"Americas","subregion":"SouthAmerica","partner_country":{"country_name":"Portugal","region":"Europe","subregion":"SouthernEurope","year":2010,"month":1,"net_weight":17105881,"usd_value":7102818}}
{"reporting_country":"Colombia","region":"Americas","subregion":"SouthAmerica","partner_country":{"country_name":"Portugal","region":"Europe","subregion":"SouthernEurope","year":2010,"month":2,"net_weight":152742932,"usd_value":16557613}}
{"reporting_country":"Colombia","region":"Americas","subregion":"SouthAmerica","partner_country":{"country_name":"Portugal","region":"Europe","subregion":"SouthernEurope","year":2010,"month":3,"net_weight":308942366,"usd_value":26419247}}
{"reporting_country":"Colombia","region":"Americas","subregion":"SouthAmerica","partner_country":{"country_name":"Rep. of Korea","region":"Asia","subregion":"EasternAsia","year":2010,"month":1,"net_weight":3218905,"usd_value":9593594}}
{"reporting_country":"Colombia","region":"Americas","subregion":"SouthAmerica","partner_country":{"country_name":"Rep. of Korea","region":"Asia","subregion":"EasternAsia","year":2010,"month":2,"net_weight":4248820,"usd_value":13568111}}
{"reporting_country":"Colombia","region":"Americas","subregion":"SouthAmerica","partner_country":{"country_name":"Rep. of Korea","region":"Asia","subregion":"EasternAsia","year":2010,"month":3,"net_weight":27636287,"usd_value":17221858}}
{"reporting_country":"Colombia","region":"Americas","subregion":"SouthAmerica","partner_country":{"country_name":"Rep. of Moldova","region":"Europe","subregion":"EasternEurope","year":2010,"month":2,"net_weight":10,"usd_value":132}}
{"reporting_country":"Colombia","region":"Americas","subregion":"SouthAmerica","partner_country":{"country_name":"Romania","region":"Europe","subregion":"EasternEurope","year":2010,"month":1,"net_weight":449,"usd_value":2145}}
{"reporting_country":"Colombia","region":"Americas","subregion":"SouthAmerica","partner_country":{"country_name":"Romania","region":"Europe","subregion":"EasternEurope","year":2010,"month":2,"net_weight":146071448,"usd_value":15019731}}
{"reporting_country":"Colombia","region":"Americas","subregion":"SouthAmerica","partner_country":{"country_name":"Romania","region":"Europe","subregion":"EasternEurope","year":2010,"month":3,"net_weight":78943,"usd_value":337420}}
{"reporting_country":"Colombia","region":"Americas","subregion":"SouthAmerica","partner_country":{"country_name":"Russian Federation","region":"Europe","subregion":"EasternEurope","year":2010,"month":1,"net_weight":1489987,"usd_value":7696501}}
{"reporting_country":"Colombia","region":"Americas","subregion":"SouthAmerica","partner_country":{"country_name":"Russian Federation","region":"Europe","subregion":"EasternEurope","year":2010,"month":2,"net_weight":1290158,"usd_value":8218927}}
{"reporting_country":"Colombia","region":"Americas","subregion":"SouthAmerica","partner_country":{"country_name":"Russian Federation","region":"Europe","subregion":"EasternEurope","year":2010,"month":3,"net_weight":1275548,"usd_value":8885734}}
{"reporting_country":"Colombia","region":"Americas","subregion":"SouthAmerica","partner_country":{"country_name":"Rwanda","region":"Africa","subregion":"EasternAfrica","year":2010,"month":1,"net_weight":3840,"usd_value":76575}}
{"reporting_country":"Colombia","region":"Americas","subregion":"SouthAmerica","partner_country":{"country_name":"Senegal","region":"Africa","subregion":"WesternAfrica","year":2010,"month":1,"net_weight":721707,"usd_value":428054}}
{"reporting_country":"Colombia","region":"Americas","subregion":"SouthAmerica","partner_country":{"country_name":"Senegal","region":"Africa","subregion":"WesternAfrica","year":2010,"month":2,"net_weight":19464,"usd_value":40550}}
{"reporting_country":"Colombia","region":"Americas","subregion":"SouthAmerica","partner_country":{"country_name":"Senegal","region":"Africa","subregion":"WesternAfrica","year":2010,"month":3,"net_weight":78800,"usd_value":180744}}
{"reporting_country":"Colombia","region":"Americas","subregion":"SouthAmerica","partner_country":{"country_name":"Singapore","region":"Asia","subregion":"South-EasternAsia","year":2010,"month":1,"net_weight":291136,"usd_value":1789044}}
{"reporting_country":"Colombia","region":"Americas","subregion":"SouthAmerica","partner_country":{"country_name":"Singapore","region":"Asia","subregion":"South-EasternAsia","year":2010,"month":2,"net_weight":123612,"usd_value":502044}}
{"reporting_country":"Colombia","region":"Americas","subregion":"SouthAmerica","partner_country":{"country_name":"Singapore","region":"Asia","subregion":"South-EasternAsia","year":2010,"month":3,"net_weight":193568,"usd_value":407596}}
{"reporting_country":"Colombia","region":"Americas","subregion":"SouthAmerica","partner_country":{"country_name":"Slovakia","region":"Europe","subregion":"EasternEurope","year":2010,"month":1,"net_weight":9011,"usd_value":62314}}
{"reporting_country":"Colombia","region":"Americas","subregion":"SouthAmerica","partner_country":{"country_name":"Slovakia","region":"Europe","subregion":"EasternEurope","year":2010,"month":2,"net_weight":12708,"usd_value":79783}}
{"reporting_country":"Colombia","region":"Americas","subregion":"SouthAmerica","partner_country":{"country_name":"Slovakia","region":"Europe","subregion":"EasternEurope","year":2010,"month":3,"net_weight":27224,"usd_value":164472}}
{"reporting_country":"Colombia","region":"Americas","subregion":"SouthAmerica","partner_country":{"country_name":"Slovenia","region":"Europe","subregion":"SouthernEurope","year":2010,"month":2,"net_weight":65651,"usd_value":362788}}
{"reporting_country":"Colombia","region":"Americas","subregion":"SouthAmerica","partner_country":{"country_name":"Slovenia","region":"Europe","subregion":"SouthernEurope","year":2010,"month":3,"net_weight":26004,"usd_value":128305}}
{"reporting_country":"Colombia","region":"Americas","subregion":"SouthAmerica","partner_country":{"country_name":"South Africa","region":"Africa","subregion":"SouthernAfrica","year":2010,"month":1,"net_weight":76271503,"usd_value":38255192}}
{"reporting_country":"Colombia","region":"Americas","subregion":"SouthAmerica","partner_country":{"country_name":"South Africa","region":"Africa","subregion":"SouthernAfrica","year":2010,"month":2,"net_weight":1186851,"usd_value":4730279}}
{"reporting_country":"Colombia","region":"Americas","subregion":"SouthAmerica","partner_country":{"country_name":"South Africa","region":"Africa","subregion":"SouthernAfrica","year":2010,"month":3,"net_weight":1692285,"usd_value":2888787}}
{"reporting_country":"Colombia","region":"Americas","subregion":"SouthAmerica","partner_country":{"country_name":"Spain","region":"Europe","subregion":"SouthernEurope","year":2010,"month":1,"net_weight":225129135,"usd_value":42179751}}
{"reporting_country":"Colombia","region":"Americas","subregion":"SouthAmerica","partner_country":{"country_name":"Spain","region":"Europe","subregion":"SouthernEurope","year":2010,"month":2,"net_weight":203205412,"usd_value":46136632}}
{"reporting_country":"Colombia","region":"Americas","subregion":"SouthAmerica","partner_country":{"country_name":"Spain","region":"Europe","subregion":"SouthernEurope","year":2010,"month":3,"net_weight":470349912,"usd_value":54340891}}
{"reporting_country":"Colombia","region":"Americas","subregion":"SouthAmerica","partner_country":{"country_name":"Sri Lanka","region":"Asia","subregion":"SouthernAsia","year":2010,"month":1,"net_weight":12544030,"usd_value":5707391}}
{"reporting_country":"Colombia","region":"Americas","subregion":"SouthAmerica","partner_country":{"country_name":"Sri Lanka","region":"Asia","subregion":"SouthernAsia","year":2010,"month":2,"net_weight":7550000,"usd_value":4076894}}
{"reporting_country":"Colombia","region":"Americas","subregion":"SouthAmerica","partner_country":{"country_name":"Sri Lanka","region":"Asia","subregion":"SouthernAsia","year":2010,"month":3,"net_weight":8545588,"usd_value":5142198}}
{"reporting_country":"Colombia","region":"Americas","subregion":"SouthAmerica","partner_country":{"country_name":"Sweden","region":"Europe","subregion":"NorthernEurope","year":2010,"month":1,"net_weight":487974,"usd_value":2050741}}
{"reporting_country":"Colombia","region":"Americas","subregion":"SouthAmerica","partner_country":{"country_name":"Sweden","region":"Europe","subregion":"NorthernEurope","year":2010,"month":2,"net_weight":755639,"usd_value":3468020}}
{"reporting_country":"Colombia","region":"Americas","subregion":"SouthAmerica","partner_country":{"country_name":"Sweden","region":"Europe","subregion":"NorthernEurope","year":2010,"month":3,"net_weight":1692192,"usd_value":4158165}}
{"reporting_country":"Colombia","region":"Americas","subregion":"SouthAmerica","partner_country":{"country_name":"Switzerland","region":"Europe","subregion":"WesternEurope","year":2010,"month":1,"net_weight":209291,"usd_value":65424290}}
{"reporting_country":"Colombia","region":"Americas","subregion":"SouthAmerica","partner_country":{"country_name":"Switzerland","region":"Europe","subregion":"WesternEurope","year":2010,"month":2,"net_weight":67008,"usd_value":65610782}}
{"reporting_country":"Colombia","region":"Americas","subregion":"SouthAmerica","partner_country":{"country_name":"Switzerland","region":"Europe","subregion":"WesternEurope","year":2010,"month":3,"net_weight":19995263,"usd_value":74976913}}
{"reporting_country":"Colombia","region":"Americas","subregion":"SouthAmerica","partner_country":{"country_name":"TFYR of Macedonia","region":"Europe","subregion":"SouthernEurope","year":2010,"month":3,"net_weight":353,"usd_value":2285}}
{"reporting_country":"Colombia","region":"Americas","subregion":"SouthAmerica","partner_country":{"country_name":"Thailand","region":"Asia","subregion":"South-EasternAsia","year":2010,"month":1,"net_weight":3994916,"usd_value":2125014}}
{"reporting_country":"Colombia","region":"Americas","subregion":"SouthAmerica","partner_country":{"country_name":"Thailand","region":"Asia","subregion":"South-EasternAsia","year":2010,"month":2,"net_weight":3959297,"usd_value":4823571}}
{"reporting_country":"Colombia","region":"Americas","subregion":"SouthAmerica","partner_country":{"country_name":"Thailand","region":"Asia","subregion":"South-EasternAsia","year":2010,"month":3,"net_weight":8704089,"usd_value":4946391}}
{"reporting_country":"Colombia","region":"Americas","subregion":"SouthAmerica","partner_country":{"country_name":"Togo","region":"Africa","subregion":"WesternAfrica","year":2010,"month":1,"net_weight":526000,"usd_value":299572}}
{"reporting_country":"Colombia","region":"Americas","subregion":"SouthAmerica","partner_country":{"country_name":"Turkey","region":"Asia","subregion":"WesternAsia","year":2010,"month":1,"net_weight":160331505,"usd_value":12238638}}
{"reporting_country":"Colombia","region":"Americas","subregion":"SouthAmerica","partner_country":{"country_name":"Turkey","region":"Asia","subregion":"WesternAsia","year":2010,"month":2,"net_weight":157354242,"usd_value":14324759}}
{"reporting_country":"Colombia","region":"Americas","subregion":"SouthAmerica","partner_country":{"country_name":"Turkey","region":"Asia","subregion":"WesternAsia","year":2010,"month":3,"net_weight":319593732,"usd_value":27152133}}
{"reporting_country":"Colombia","region":"Americas","subregion":"SouthAmerica","partner_country":{"country_name":"Ukraine","region":"Europe","subregion":"EasternEurope","year":2010,"month":1,"net_weight":56634,"usd_value":93915}}
{"reporting_country":"Colombia","region":"Americas","subregion":"SouthAmerica","partner_country":{"country_name":"Ukraine","region":"Europe","subregion":"EasternEurope","year":2010,"month":2,"net_weight":138539,"usd_value":394750}}
{"reporting_country":"Colombia","region":"Americas","subregion":"SouthAmerica","partner_country":{"country_name":"Ukraine","region":"Europe","subregion":"EasternEurope","year":2010,"month":3,"net_weight":185481,"usd_value":1869614}}
{"reporting_country":"Colombia","region":"Americas","subregion":"SouthAmerica","partner_country":{"country_name":"United Rep. of Tanzania","region":"Africa","subregion":"EasternAfrica","year":2010,"month":1,"net_weight":124145,"usd_value":348242}}
{"reporting_country":"Colombia","region":"Americas","subregion":"SouthAmerica","partner_country":{"country_name":"United Rep. of Tanzania","region":"Africa","subregion":"EasternAfrica","year":2010,"month":2,"net_weight":126089,"usd_value":361666}}
{"reporting_country":"Colombia","region":"Americas","subregion":"SouthAmerica","partner_country":{"country_name":"United Rep. of Tanzania","region":"Africa","subregion":"EasternAfrica","year":2010,"month":3,"net_weight":141067,"usd_value":277290}}
{"reporting_country":"Colombia","region":"Americas","subregion":"SouthAmerica","partner_country":{"country_name":"Uruguay","region":"Americas","subregion":"SouthAmerica","year":2010,"month":1,"net_weight":30277,"usd_value":160128}}
{"reporting_country":"Colombia","region":"Americas","subregion":"SouthAmerica","partner_country":{"country_name":"Uruguay","region":"Americas","subregion":"SouthAmerica","year":2010,"month":2,"net_weight":153829,"usd_value":335286}}
{"reporting_country":"Colombia","region":"Americas","subregion":"SouthAmerica","partner_country":{"country_name":"Uruguay","region":"Americas","subregion":"SouthAmerica","year":2010,"month":3,"net_weight":361366,"usd_value":1192103}}
{"reporting_country":"Colombia","region":"Americas","subregion":"SouthAmerica","partner_country":{"country_name":"USA","region":"Americas","subregion":"NorthernAmerica","year":2010,"month":1,"net_weight":3061975267,"usd_value":1316013184}}
{"reporting_country":"Colombia","region":"Americas","subregion":"SouthAmerica","partner_country":{"country_name":"USA","region":"Americas","subregion":"NorthernAmerica","year":2010,"month":2,"net_weight":2592770554,"usd_value":1220492967}}
{"reporting_country":"Colombia","region":"Americas","subregion":"SouthAmerica","partner_country":{"country_name":"USA","region":"Americas","subregion":"NorthernAmerica","year":2010,"month":3,"net_weight":3339718452,"usd_value":1518651754}}
{"reporting_country":"Colombia","region":"Americas","subregion":"SouthAmerica","partner_country":{"country_name":"Zimbabwe","region":"Africa","subregion":"EasternAfrica","year":2010,"month":1,"net_weight":93132,"usd_value":174079}}
{"reporting_country":"Colombia","region":"Americas","subregion":"SouthAmerica","partner_country":{"country_name":"Zimbabwe","region":"Africa","subregion":"EasternAfrica","year":2010,"month":2,"net_weight":91696,"usd_value":166375}}
{"reporting_country":"Colombia","region":"Americas","subregion":"SouthAmerica","partner_country":{"country_name":"Zimbabwe","region":"Africa","subregion":"EasternAfrica","year":2010,"month":3,"net_weight":70297,"usd_value":130681}}
]